basicCals/__init__.py
basicCals-0.0.6.dist-info/LICENSE.txt
basicCals-0.0.6.dist-info/METADATA
basicCals-0.0.6.dist-info/WHEEL
basicCals-0.0.6.dist-info/top_level.txt
basicCals-0.0.6.dist-info/RECORD
