Metadata-Version: 2.1
Name: basicCals
Version: 0.0.6
Summary: Basic Mathematics Module
Home-page: UNKNOWN
Author: XakedowX
Author-email: thecode113@gmail.com
License: UNKNOWN
Platform: UNKNOWN
Classifier: Programming Language :: Python :: 3
Classifier: License :: OSI Approved :: BSD License
Classifier: Operating System :: OS Independent
Requires-Python: >=3.6
